{"box_data": [{"position": {"minX": 243.5, "minY": 61.6875, "maxX": 353.0, "maxY": 201.0}, "class_id": 1, "box_caption": "face 0.972", "scores": {"class_score": 0.97216796875}, "domain": "pixel"}, {"position": {"minX": 220.75, "minY": 94.5625, "maxX": 291.75, "maxY": 223.0}, "class_id": 2, "box_caption": "phone_call 0.881", "scores": {"class_score": 0.88134765625}, "domain": "pixel"}, {"position": {"minX": 229.375, "minY": 83.125, "maxX": 315.0, "maxY": 217.875}, "class_id": 2, "box_caption": "phone_call 0.014", "scores": {"class_score": 0.0144805908203125}, "domain": "pixel"}, {"position": {"minX": 232.75, "minY": 316.5, "maxX": 274.0, "maxY": 355.5}, "class_id": 1, "box_caption": "face 0.003", "scores": {"class_score": 0.003437042236328125}, "domain": "pixel"}, {"position": {"minX": 183.625, "minY": 298.25, "maxX": 254.125, "maxY": 354.75}, "class_id": 3, "box_caption": "smoking 0.002", "scores": {"class_score": 0.0015163421630859375}, "domain": "pixel"}, {"position": {"minX": 179.375, "minY": 254.0, "maxX": 243.625, "maxY": 337.0}, "class_id": 1, "box_caption": "face 0.001", "scores": {"class_score": 0.0013551712036132812}, "domain": "pixel"}], "class_labels": {"0": "drinking", "1": "face", "2": "phone_call", "3": "smoking"}}